oscp/RegistrationManager.py
oscp/__init__.py
oscp/co_endpoints.py
oscp/cp_endpoints.py
oscp/ep_endpoints.py
oscp/ep_models.py
oscp/epc_endpoints.py
oscp/fp_endpoints.py
oscp/json_models.py
oscp/registration.py
pyoscp-0.1.0.dist-info/LICENSE
pyoscp-0.1.0.dist-info/WHEEL
pyoscp-0.1.0.dist-info/METADATA
pyoscp-0.1.0.dist-info/RECORD
