Metadata-Version: 2.1
Name: pyoscp
Version: 0.1.0
Summary: Python library for the Open Smart Charging Protocol (OSCP)
Home-page: https://github.com/NOWUM/pyoscp
License: MIT
Keywords: ev,charging,OpenAPI,Swagger,REST
Author: Florian Maurer
Author-email: maurer@fh-aachen.de
Requires-Python: >=3.7,<4.0
Classifier: Development Status :: 4 - Beta
Classifier: Intended Audience :: Developers
Classifier: License :: OSI Approved :: MIT License
Classifier: Operating System :: OS Independent
Classifier: Programming Language :: Python :: 3
Classifier: Programming Language :: Python :: 3.7
Classifier: Programming Language :: Python :: 3.8
Classifier: Programming Language :: Python :: 3.9
Classifier: Programming Language :: Python :: 3.10
Classifier: Programming Language :: Python :: 3.11
Classifier: Topic :: Scientific/Engineering :: Interface Engine/Protocol Translator
Classifier: Topic :: Software Development :: Libraries :: Python Modules
Requires-Dist: flask (>=2.2.2,<3.0.0)
Requires-Dist: flask-restx (>=1.0.3,<2.0.0)
Requires-Dist: importlib_metadata (>=4.0.0); python_version < "3.8"
Requires-Dist: packaging (>=21.3,<22.0)
Requires-Dist: requests (>=2.28.1,<3.0.0)
Project-URL: Repository, https://github.com/NOWUM/pyoscp
